{
  "name": "Frederick Schneider",
  "age": 26,
  "address": {
    "street": "Amusis Mill",
    "city": "Tuvivor",
    "state": "TX",
    "zip": "84313"
  },
  "contact": {
    "phone": "(768) 852-3943",
    "servicePhone": "800914561"
  },
  "birthday": "1984-02-07T19:32:50.662Z",
  "ip": "1.185.33.121",
  "foo": "bar",
  "profile": {
    "about": "Ijodala hewjupa githu puwoma kugiub cukdumo oripuno uviodza nakid rutuprog mu piazu. Ef de cut bonsam huzmecoj hugluvme udiajo mubedluz inoer depgidpi ateto ju rojfefe peg viwaknu li wi juz. Tursoctu luc kij sew ti nipjajed maugu roib zeel uz pitgug fito jefivo hep.",
    "bio": "Ref bonnocip fi wulgah leecco kicapakec mitarsi era nomnuz zawaboru mardoz adnolle do nep neiz em lecufu. Na rasu sihindiv refpi ihifi lesuwle uluhusir figujaz wo zo can gopjimep gubas gor biohivus wiwisi ucgazbuc kisuma. Kusa fevdid weol ub kosiz ceji pujtic ke pilbo katas ogmiwi ni re mefla binlugke ramenu fu ji. Footiiba safajofu saadvum duojfe wib pin ilo sogub amuzak duwijde raz baji tilo cef socgosi. Sul fofpi karisba ji wa uhoze itwodoj wi dabtivtum zol huwok la ori. Ruv oto otu bijoj ze nakpudgok wiz da disweku sud nutcid vugbeum uhe sajifa gotahabev."
  },
  "apiKey": "d4b625612c3cf7613087222269fa551e76f6d83875d746b0f908317a6872f834",
  "currency": {
    "code": "MMK",
    "name": "Myanmar (Burma) Kyat"
  }
}